autocortext_py/__init__.py
autocortext_py/client.py
autocortext_py-0.4.1.dist-info/LICENSE
autocortext_py-0.4.1.dist-info/METADATA
autocortext_py-0.4.1.dist-info/WHEEL
autocortext_py-0.4.1.dist-info/top_level.txt
autocortext_py-0.4.1.dist-info/RECORD
