Metadata-Version: 2.1
Name: autocortext-py
Version: 0.4.1
Summary: Simple client for AutoCortext API
Home-page: https://autocortext.com
Author: Mark Watson
Author-email: markus.c.watson@gmail.com
License: UNKNOWN
Keywords: autocortext
Platform: UNKNOWN
Classifier: License :: OSI Approved :: MIT License
Classifier: Programming Language :: Python :: 3
Classifier: Operating System :: OS Independent
Requires-Python: >=3.0
License-File: LICENSE
Requires-Dist: requests
Requires-Dist: datetime
